docto/__init__.py
docto/docto.py
docto-999.1.1.dist-info/LICENSE
docto-999.1.1.dist-info/WHEEL
docto-999.1.1.dist-info/METADATA
docto-999.1.1.dist-info/RECORD
